[
  {
    "name": "Gabriel",
    "lastName": "Calla",
    "email": "gabriel@giveone.com",
    "password": "$2a$10$tN2lblcKJ/15tVBp4dcfp.BsuHMJRqFh8ARr5w2so.0o/Ng422WfO",
    "rolId": 1,
    "avatar": "avatar_default.png"
  },
  {
    "name": "Carolina",
    "lastName": "Vega",
    "email": "carolina@giveone.com",
    "password": "$2a$10$ZGiAVNiEP7M8xQWqkCL2m.3wYO5yMQ4BFi7EinLQnED4KGRb.Qb7q",
    "rolId": 1,
    "avatar": "avatar_default.png"
  },
  {
    "name": "Eric",
    "lastName": "Mena",
    "email": "eric@gmail.com",
    "password": "$2a$10$MyJ9otXkRbpV7cRkoldKkOyIJ6kmkqt1Ex954zuMe1nd5v9lJ0cs6",
    "rolId": 2,
    "avatar": "avatar_default.png"
  },
  {
    "name": "Cristian",
    "lastName": "Elias",
    "email": "cristian@gmail.com",
    "password": "$2a$10$4.ilR9uO7Fo10T9dSCZ4SuUsby2KoCbz28FIbExe7C8VxhX/gwWtu",
    "rolId": 2,
    "avatar": "avatar_default.png"
  },
  {
    "name": "Admin",
    "lastName": "1",
    "email": "give@one.com.ar",
    "password": "$2a$10$uq.qwIWNl6j60BccVT3Ld.9edvlAmnf8t.yp.scGuNcv4vciACQOW",
    "rolId": 1,
    "avatar": "avatar_default.png"
  }
]